pytart.cpython-314t-x86_64-linux-gnu.so
bin/spirv-as
bin/spirv-cfg
bin/spirv-diff
bin/spirv-dis
bin/spirv-lesspipe.sh
bin/spirv-link
bin/spirv-lint
bin/spirv-objdump
bin/spirv-opt
bin/spirv-reduce
bin/spirv-val
include/spirv-tools/libspirv.h
include/spirv-tools/libspirv.hpp
include/spirv-tools/linker.hpp
include/spirv-tools/optimizer.hpp
lib64/libSPIRV-Tools-diff.a
lib64/libSPIRV-Tools-link.a
lib64/libSPIRV-Tools-lint.a
lib64/libSPIRV-Tools-opt.a
lib64/libSPIRV-Tools-reduce.a
lib64/libSPIRV-Tools-shared.so
lib64/libSPIRV-Tools.a
lib64/cmake/SPIRV-Tools/SPIRV-ToolsConfig.cmake
lib64/cmake/SPIRV-Tools/SPIRV-ToolsTarget-release.cmake
lib64/cmake/SPIRV-Tools/SPIRV-ToolsTarget.cmake
lib64/cmake/SPIRV-Tools-diff/SPIRV-Tools-diffConfig.cmake
lib64/cmake/SPIRV-Tools-diff/SPIRV-Tools-diffTargets-release.cmake
lib64/cmake/SPIRV-Tools-diff/SPIRV-Tools-diffTargets.cmake
lib64/cmake/SPIRV-Tools-link/SPIRV-Tools-linkConfig.cmake
lib64/cmake/SPIRV-Tools-link/SPIRV-Tools-linkTargets-release.cmake
lib64/cmake/SPIRV-Tools-link/SPIRV-Tools-linkTargets.cmake
lib64/cmake/SPIRV-Tools-lint/SPIRV-Tools-lintConfig.cmake
lib64/cmake/SPIRV-Tools-lint/SPIRV-Tools-lintTargets-release.cmake
lib64/cmake/SPIRV-Tools-lint/SPIRV-Tools-lintTargets.cmake
lib64/cmake/SPIRV-Tools-opt/SPIRV-Tools-optConfig.cmake
lib64/cmake/SPIRV-Tools-opt/SPIRV-Tools-optTargets-release.cmake
lib64/cmake/SPIRV-Tools-opt/SPIRV-Tools-optTargets.cmake
lib64/cmake/SPIRV-Tools-reduce/SPIRV-Tools-reduceConfig.cmake
lib64/cmake/SPIRV-Tools-reduce/SPIRV-Tools-reduceTarget-release.cmake
lib64/cmake/SPIRV-Tools-reduce/SPIRV-Tools-reduceTarget.cmake
lib64/cmake/SPIRV-Tools-tools/SPIRV-Tools-toolsConfig.cmake
lib64/cmake/SPIRV-Tools-tools/SPIRV-Tools-toolsTargets-release.cmake
lib64/cmake/SPIRV-Tools-tools/SPIRV-Tools-toolsTargets.cmake
lib64/pkgconfig/SPIRV-Tools-shared.pc
lib64/pkgconfig/SPIRV-Tools.pc
pytart.libs/libXau-154567c4.so.6.0.0
pytart.libs/libvulkan-2c7768c1.so.1.3.283
pytart-0.1.4.dist-info/METADATA
pytart-0.1.4.dist-info/WHEEL
pytart-0.1.4.dist-info/RECORD
pytart-0.1.4.dist-info/licenses/LICENSE
