Metadata-Version: 2.4
Name: pytart
Version: 0.1.4
Summary: Vulkan-based GPGPU engine
Author-Email: cookie <softcookiepp@mailfence.com>
License-File: LICENSE
Classifier: Programming Language :: Python :: 3.9
Project-URL: Repository, https://codeberg.org/softcookiepp/tart
Requires-Python: >=3.9
Requires-Dist: numpy
Provides-Extra: test
Requires-Dist: pytest; extra == "test"
Requires-Dist: numpy; extra == "test"
